skill_extractor/__init__.py
skill_extractor/emsi_skills_full.csv
skill_extractor/match.py
skill_extractor_alanjtu-0.0.1.dist-info/LICENSE
skill_extractor_alanjtu-0.0.1.dist-info/METADATA
skill_extractor_alanjtu-0.0.1.dist-info/WHEEL
skill_extractor_alanjtu-0.0.1.dist-info/top_level.txt
skill_extractor_alanjtu-0.0.1.dist-info/RECORD
