Metadata-Version: 2.1
Name: skill-extractor-alanjtu
Version: 0.0.1
Summary: skill extractor, first packaged version
Home-page: https://github.com/edyoucated/skill-extractor
Author: Alan Tu
Author-email: alan@edyoucated.org
License: UNKNOWN
Project-URL: Bug Tracker, https://github.com/edyoucated/skill-extractor
Platform: UNKNOWN
Classifier: Programming Language :: Python :: 3
Classifier: License :: OSI Approved :: MIT License
Classifier: Operating System :: OS Independent
Requires-Python: >=3.6
License-File: LICENSE
